openiti/__init__.py
openiti/corpus/__init__.py
openiti/corpus/collect_bookIDs.py
openiti/corpus/insert_milestones.py
openiti/corpus/replace_regex_patterns.py
openiti/git/__init__.py
openiti/git/check_ymls.py
openiti/git/clone_OpenITI.py
openiti/git/collect_txt_files.py
openiti/git/commit_push.py
openiti/git/get_issues.py
openiti/git/git_util.py
openiti/git/initialize_texts.py
openiti/git/resolve_URI_change_issues.py
openiti/helper/__init__.py
openiti/helper/ara.py
openiti/helper/funcs.py
openiti/helper/quran.py
openiti/helper/rgx.py
openiti/helper/templates.py
openiti/helper/uri.py
openiti/helper/yml.py
openiti/instantiations/__init__.py
openiti/instantiations/generate_imech_instantiation.py
openiti/instantiations/generate_istylo_instantiation.py
openiti/new_books/__init__.py
openiti/new_books/add/__init__.py
openiti/new_books/add/add_books.py
openiti/new_books/convert/__init__.py
openiti/new_books/convert/epub_converter_generic.py
openiti/new_books/convert/epub_converter_ghaemiyeh.py
openiti/new_books/convert/epub_converter_hindawi.py
openiti/new_books/convert/epub_converter_masaha.py
openiti/new_books/convert/generic_converter.py
openiti/new_books/convert/html2md.py
openiti/new_books/convert/html2md_hindawi.py
openiti/new_books/convert/html_converter_Rafed.py
openiti/new_books/convert/html_converter_eShia.py
openiti/new_books/convert/html_converter_generic.py
openiti/new_books/convert/html_converter_ghbook.py
openiti/new_books/convert/html_converter_noorlib.py
openiti/new_books/convert/md2html.py
openiti/new_books/convert/shamelaAY_converter.py
openiti/new_books/convert/shamela_converter.py
openiti/new_books/convert/tei_converter_GRAR.py
openiti/new_books/convert/tei_converter_LAL.py
openiti/new_books/convert/tei_converter_Thielen.py
openiti/new_books/convert/tei_converter_Wuerzburg.py
openiti/new_books/convert/tei_converter_generic.py
openiti/new_books/convert/yml2json.py
openiti/new_books/convert/helper/__init__.py
openiti/new_books/convert/helper/bok.py
openiti-0.1.5.10.dist-info/LICENSE
openiti-0.1.5.10.dist-info/METADATA
openiti-0.1.5.10.dist-info/WHEEL
openiti-0.1.5.10.dist-info/top_level.txt
openiti-0.1.5.10.dist-info/RECORD
