Metadata-Version: 2.1
Name: openiti
Version: 0.1.5.10
Summary: A package for dealing with the openITI corpus
Home-page: https://github.com/OpenITI
Author: Sohail Merchant, Maxim Romanov, Masoumeh Seydi, Peter Verkinderen
Author-email: peter.verkinderen@gmail.com
License: UNKNOWN
Platform: UNKNOWN
Classifier: Programming Language :: Python :: 3
Classifier: License :: OSI Approved :: MIT License
Classifier: Operating System :: OS Independent
Requires-Python: >=3.4
License-File: LICENSE
Requires-Dist: beautifulsoup4
Requires-Dist: requests
Requires-Dist: six
Requires-Dist: sphinx-rtd-theme
Requires-Dist: pypyodbc
Requires-Dist: bs4
Requires-Dist: pygithub
